pdfreader/__init__.py
pdfreader/buffer.py
pdfreader/constants.py
pdfreader/document.py
pdfreader/exceptions.py
pdfreader/pillow.py
pdfreader/registry.py
pdfreader/securityhandler.py
pdfreader/tests.py
pdfreader/utils.py
pdfreader/codecs/__init__.py
pdfreader/codecs/agl.py
pdfreader/codecs/codec.py
pdfreader/codecs/decoder.py
pdfreader/codecs/differences.py
pdfreader/codecs/macroman.py
pdfreader/codecs/pdfdoc.py
pdfreader/codecs/standard.py
pdfreader/codecs/tests.py
pdfreader/codecs/winansi.py
pdfreader/codecs/zapfdingbatsgl.py
pdfreader/codecs/cmaps/Adobe-CNS1-0
pdfreader/codecs/cmaps/Adobe-CNS1-3
pdfreader/codecs/cmaps/Adobe-CNS1-4
pdfreader/codecs/cmaps/Adobe-GB1-0
pdfreader/codecs/cmaps/Adobe-GB1-2
pdfreader/codecs/cmaps/Adobe-GB1-4
pdfreader/codecs/cmaps/Adobe-Japan1-1
pdfreader/codecs/cmaps/Adobe-Japan1-2
pdfreader/codecs/cmaps/Adobe-Japan1-4
pdfreader/codecs/cmaps/Adobe-Japan1-5
pdfreader/codecs/cmaps/Adobe-Korea1-0
pdfreader/codecs/cmaps/Adobe-Korea1-1
pdfreader/codecs/cmaps/Adobe-Korea1-2
pdfreader/codecs/cmaps/Identity-H
pdfreader/codecs/cmaps/README.md
pdfreader/filters/__init__.py
pdfreader/filters/ascii85.py
pdfreader/filters/asciihex.py
pdfreader/filters/ccittfax.py
pdfreader/filters/crypt.py
pdfreader/filters/dct.py
pdfreader/filters/flate.py
pdfreader/filters/jbig2.py
pdfreader/filters/jpx.py
pdfreader/filters/lzw.py
pdfreader/filters/predictors.py
pdfreader/filters/runlength.py
pdfreader/filters/test_ccittf_fax.py
pdfreader/filters/tests.py
pdfreader/parsers/__init__.py
pdfreader/parsers/base.py
pdfreader/parsers/cmap.py
pdfreader/parsers/content.py
pdfreader/parsers/document.py
pdfreader/parsers/inlineimage.py
pdfreader/parsers/objstm.py
pdfreader/parsers/tests.py
pdfreader/types/__init__.py
pdfreader/types/cmap.py
pdfreader/types/constants.py
pdfreader/types/content.py
pdfreader/types/filestructure.py
pdfreader/types/native.py
pdfreader/types/objects.py
pdfreader/types/tests.py
pdfreader/types/xref.py
pdfreader/viewer/__init__.py
pdfreader-0.1.15.dist-info/LICENSE
pdfreader-0.1.15.dist-info/METADATA
pdfreader-0.1.15.dist-info/WHEEL
pdfreader-0.1.15.dist-info/top_level.txt
pdfreader-0.1.15.dist-info/RECORD
