Metadata-Version: 2.1
Name: pdfreader
Version: 0.1.15
Summary: Pythonic API for parsing PDF files
Home-page: http://github.com/maxpmaxp/pdfreader
Author: Maksym Polshcha
Author-email: maxp@sterch.net
Maintainer: Maksym Polshcha
Maintainer-email: maxp@sterch.net
License: MIT Licence
Keywords: pdf,pdfreader,pdfparser,adobe,parser,cmap
Classifier: Development Status :: 5 - Production/Stable
Classifier: Intended Audience :: Developers
Classifier: License :: OSI Approved :: MIT License
Classifier: Operating System :: MacOS :: MacOS X
Classifier: Operating System :: POSIX
Classifier: Programming Language :: Python :: 3.6
Classifier: Programming Language :: Python :: 3.7
Classifier: Topic :: Software Development
Classifier: Topic :: Software Development :: Libraries :: Python Modules
Requires-Python: >=3.4
License-File: LICENSE
Requires-Dist: bitarray>=1.1.0
Requires-Dist: pillow>=7.1.0
Requires-Dist: pycryptodome>=3.9.9
Requires-Dist: python-dateutil>=2.8.1
